{
  "project_info": {
    "project_number": "827390420784",
    "project_id": "app-f4755",
    "storage_bucket": "app-f4755.appspot.com"
  },
  "client": [
    {
      "client_info": {
        "mobilesdk_app_id": "1:827390420784:android:a192d7c36120bf72210af5",
        "android_client_info": {
          "package_name": "com.example.app_2100"
        }
      },
      "oauth_client": [],
      "api_key": [
        {
          "current_key": "AIzaSyBji3HTrFy2jiK97xWtVgKOvuEWWOO4HKQ"
        }
      ],
      "services": {
        "appinvite_service": {
          "other_platform_oauth_client": []
        }
      }
    }
  ],
  "configuration_version": "1"
}